nonblocking_logging/__init__.py
nonblocking_logging/handlers/__init__.py
nonblocking_logging/handlers/telegram.py
nonblocking_logging/integrations/__init__.py
nonblocking_logging/integrations/django/__init__.py
nonblocking_logging/integrations/django/apps.py
nonblocking_logging/integrations/django/conf.py
nonblocking_logging/integrations/django/handlers/__init__.py
nonblocking_logging/integrations/django/handlers/telegram.py
nonblocking_logging/integrations/django/startup.py
nonblocking_logging-0.1.2.dist-info/LICENSE
nonblocking_logging-0.1.2.dist-info/METADATA
nonblocking_logging-0.1.2.dist-info/WHEEL
nonblocking_logging-0.1.2.dist-info/RECORD
