Metadata-Version: 2.1
Name: nonblocking-logging
Version: 0.1.2
Summary: 
Home-page: https://github.com/ersain/nonblocking-logging
License: MIT
Keywords: nonblocking,logging
Author: Ersain Dinmukhamed
Requires-Python: >=3.8,<4.0
Classifier: License :: OSI Approved :: MIT License
Classifier: Programming Language :: Python :: 3
Classifier: Programming Language :: Python :: 3.8
Classifier: Programming Language :: Python :: 3.9
Classifier: Programming Language :: Python :: 3.10
Classifier: Programming Language :: Python :: 3.11
Requires-Dist: requests (>=2.31.0,<3.0.0)
Project-URL: Repository, https://github.com/ersain/nonblocking-logging
